sax/__init__.py
sax/api/__init__.py
sax/api/app.py
sax/api/exceptions/__init__.py
sax/api/exceptions/badrequest.py
sax/api/exceptions/notfound.py
sax/api/exceptions/validation.py
sax/api/routes/__init__.py
sax/api/routes/sax_routes.py
sax/api/state/__init__.py
sax/api/state/state.py
sax/core/__init__.py
sax/core/causal_process_discovery/__init__.py
sax/core/causal_process_discovery/causal_constants.py
sax/core/causal_process_discovery/causal_discovery.py
sax/core/causal_process_discovery/prior_knowledge.py
sax/core/causal_process_discovery/algorithms/__init__.py
sax/core/causal_process_discovery/algorithms/base_causal_alg.py
sax/core/causal_process_discovery/algorithms/lingam.py
sax/core/causal_process_discovery/algorithms/positive_lingam.py
sax/core/causal_process_discovery/algorithms/positive_lingam_impl/__init__.py
sax/core/causal_process_discovery/algorithms/positive_lingam_impl/base_positive_lingam.py
sax/core/causal_process_discovery/algorithms/positive_lingam_impl/positive_direct_lingam.py
sax/core/causal_process_discovery/modalities/__init__.py
sax/core/causal_process_discovery/modalities/base_anchor.py
sax/core/causal_process_discovery/modalities/chain_anchor.py
sax/core/causal_process_discovery/modalities/parent_anchor.py
sax/core/process_data/__init__.py
sax/core/process_data/data.py
sax/core/process_data/discovery_result.py
sax/core/process_data/raw_event_data.py
sax/core/process_data/tabular_data.py
sax/core/process_data/formatters/__init__.py
sax/core/process_data/formatters/base_formatter.py
sax/core/process_data/formatters/csv_formatter.py
sax/core/process_data/formatters/mxml_formatter.py
sax/core/process_data/formatters/xes_formatter.py
sax/core/process_mining/__init__.py
sax/core/process_mining/process_mining.py
sax/core/process_xai/__init__.py
sax/core/process_xai/xai.py
sax/core/synthesis/__init__.py
sax/core/synthesis/sax_explainability.py
sax/core/synthesis/exceptions/__init__.py
sax/core/synthesis/exceptions/llm_api_error.py
sax4bpm-0.3.1.dist-info/licenses/LICENSE
sax4bpm-0.3.1.dist-info/METADATA
sax4bpm-0.3.1.dist-info/WHEEL
sax4bpm-0.3.1.dist-info/top_level.txt
sax4bpm-0.3.1.dist-info/RECORD
